{
    "result_type": 1,
    "syanten": 1,
    "time": 49609,
    "candidates": [
        {
            "tile": 1,
            "syanten_down": false,
            "required_tiles": [
                {
                    "tile": 10,
                    "count": 4
                },
                {
                    "tile": 11,
                    "count": 2
                },
                {
                    "tile": 12,
                    "count": 3
                },
                {
                    "tile": 13,
                    "count": 4
                },
                {
                    "tile": 18,
                    "count": 2
                },
                {
                    "tile": 19,
                    "count": 3
                },
                {
                    "tile": 20,
                    "count": 2
                },
                {
                    "tile": 21,
                    "count": 3
                },
                {
                    "tile": 23,
                    "count": 3
                },
                {
                    "tile": 24,
                    "count": 4
                }
            ],
            "exp_values": [
                7654.592394607594,
                7364.0729623977899,
                7043.462515652547,
                6691.668907379313,
                6306.480748355266,
                5888.534394304086,
                5445.81602582283,
                4991.393846740481,
                4504.666332640081,
                3986.6217320419057,
                3434.825159903312,
                2851.474206239641,
                2242.224138387116,
                1625.6357238573785,
                1017.1437148798842,
                372.319618631797,
                0.0
            ],
            "win_probs": [
                0.5640390670185806,
                0.5406321178982799,
                0.5153731981906912,
                0.48722066944473199,
                0.45638706536467896,
                0.423906033309228,
                0.38928716900808799,
                0.35836493437949376,
                0.3191617733729949,
                0.2777176195293919,
                0.23425495822822846,
                0.18873489979669429,
                0.14304972638001296,
                0.09717620232520616,
                0.05443484394286721,
                0.01868823000898473,
                0.0
            ],
            "tenpai_probs": [
                0.9696693035128952,
                0.9715145735117464,
                0.9720274193604956,
                0.9708575410653656,
                0.9679682899202474,
                0.9738864872504549,
                0.9716851092638948,
                1.0102279212848882,
                1.0019783550171464,
                0.9874032886344639,
                0.9750699758141443,
                0.9404095914421268,
                0.8878772501905816,
                0.8098398610213108,
                0.695291835655087,
                0.44330637915543616,
                0.2857142857142857
            ]
        },
        {
            "tile": 2,
            "syanten_down": false,
            "required_tiles": [
                {
                    "tile": 10,
                    "count": 4
                },
                {
                    "tile": 13,
                    "count": 4
                },
                {
                    "tile": 19,
                    "count": 3
                }
            ],
            "exp_values": [
                4163.564390881705,
                3929.57462805334,
                3683.965457279541,
                3426.4401105591784,
                3158.426229991204,
                2880.1419678616964,
                2591.869347204282,
                2295.0869245406818,
                1994.290011359622,
                1690.953427849529,
                1388.3981321533489,
                1091.029148374973,
                805.0361932296163,
                537.3098821522222,
                295.14169003757157,
                83.46884676215723,
                0.0
            ],
            "win_probs": [
                0.3206420760623036,
                0.30152269773695,
                0.2832099888938146,
                0.262060085804683,
                0.23826863282281258,
                0.21574489986317375,
                0.19249906585651717,
                0.16829176609205058,
                0.1444238734361423,
                0.12059059727288282,
                0.09703656813583,
                0.07429793319928058,
                0.05251005269663421,
                0.032911977986332909,
                0.016227926543567526,
                0.004312668463611859,
                0.0
            ],
            "tenpai_probs": [
                0.8606338854361294,
                0.8524652640847017,
                0.8432575762644892,
                0.8306730664482686,
                0.8153009025148907,
                0.7966806474883174,
                0.774267125235533,
                0.7474123025636252,
                0.7153426317039776,
                0.6771305270125315,
                0.631658204661041,
                0.5804402304768725,
                0.5162934543471929,
                0.4403045663493556,
                0.3479456885910775,
                0.2208445642407905,
                0.10476190476190477
            ]
        },
        {
            "tile": 3,
            "syanten_down": false,
            "required_tiles": [
                {
                    "tile": 10,
                    "count": 4
                },
                {
                    "tile": 13,
                    "count": 4
                },
                {
                    "tile": 19,
                    "count": 3
                }
            ],
            "exp_values": [
                4265.219750318213,
                4030.6195331314049,
                3783.3985921478135,
                3523.456155307947,
                3251.022165521553,
                2966.5974936437635,
                2671.039198094599,
                2365.672244316739,
                2053.037378032887,
                1743.9084225192476,
                1435.2034338903139,
                1130.6099759878173,
                836.0355882124675,
                558.6965439050209,
                306.3849153203281,
                83.46884676215723,
                0.0
            ],
            "win_probs": [
                0.3313213584037754,
                0.3116850597013744,
                0.29133204018206457,
                0.2699549051768904,
                0.24758349684797904,
                0.22427441825667195,
                0.20011981172318914,
                0.17525895297373973,
                0.15026732696085377,
                0.12554025180860599,
                0.10116440992365875,
                0.07751322809683464,
                0.054816836243343849,
                0.03419566798747426,
                0.016816552048433556,
                0.004312668463611859,
                0.0
            ],
            "tenpai_probs": [
                0.8635960111217798,
                0.8574738751829988,
                0.8478765910126638,
                0.8359497253749598,
                0.8213039257946773,
                0.8034760443367838,
                0.7819124771150559,
                0.7559480141225293,
                0.7252325911543682,
                0.6879400521782533,
                0.6432662837225569,
                0.59259821148474,
                0.528559442602724,
                0.45132289127175387,
                0.35826552804158176,
                0.224797843665768,
                0.10476190476190477
            ]
        },
        {
            "tile": 11,
            "syanten_down": false,
            "required_tiles": [
                {
                    "tile": 1,
                    "count": 2
                },
                {
                    "tile": 4,
                    "count": 4
                },
                {
                    "tile": 12,
                    "count": 3
                },
                {
                    "tile": 19,
                    "count": 3
                }
            ],
            "exp_values": [
                3286.834239561145,
                3113.609708591008,
                2932.904638237431,
                2743.5561129212576,
                2544.7202675955179,
                2336.4001752992796,
                2119.1471093172497,
                1893.4160947979115,
                1665.238413141626,
                1434.8035301818453,
                1201.6414766545857,
                966.1097007103539,
                731.6966727599694,
                503.0810822729038,
                280.5163847550149,
                68.98041923770912,
                0.0
            ],
            "win_probs": [
                0.30924970771620488,
                0.2944519289321996,
                0.2797182839766268,
                0.26031328353749669,
                0.24002724085105449,
                0.21831286589130526,
                0.1956846782646038,
                0.17245170357321608,
                0.15025548468490022,
                0.12715942509684884,
                0.10335848771841323,
                0.07975169908431955,
                0.05692478506907512,
                0.03572355344823459,
                0.017468154604462127,
                0.004043126684636119,
                0.0
            ],
            "tenpai_probs": [
                0.8995617008855449,
                0.8957003558036566,
                0.8960238413946501,
                0.8884968532539882,
                0.8791196795506391,
                0.8664052598611715,
                0.8521285787918612,
                0.8320441193214603,
                0.8133611887645785,
                0.7835247658971366,
                0.7447188910432618,
                0.697104536997182,
                0.6341632052399369,
                0.5527584881402547,
                0.44622347616528526,
                0.24528301886792448,
                0.11428571428571428
            ]
        },
        {
            "tile": 12,
            "syanten_down": false,
            "required_tiles": [
                {
                    "tile": 1,
                    "count": 2
                },
                {
                    "tile": 4,
                    "count": 4
                },
                {
                    "tile": 11,
                    "count": 2
                },
                {
                    "tile": 19,
                    "count": 3
                }
            ],
            "exp_values": [
                2932.6990740189687,
                2784.674680568934,
                2629.060174017934,
                2464.6750296289148,
                2291.4097084874049,
                2110.1733002943117,
                1921.4246474836683,
                1724.6698467659524,
                1521.9272381843987,
                1313.9803826978235,
                1101.1538835566026,
                885.8230313036644,
                671.6752074005581,
                462.7180118429859,
                259.56925154324997,
                60.58675458332405,
                0.0
            ],
            "win_probs": [
                0.3193805633047888,
                0.3062323898469026,
                0.28720163867324557,
                0.26710575646505715,
                0.24601807286630043,
                0.22466350565484059,
                0.2018065622345626,
                0.17777015113176784,
                0.15417724385099169,
                0.129699355594049,
                0.10512983870849442,
                0.08090114007437621,
                0.05742537708759435,
                0.03572391109568563,
                0.017199452519501888,
                0.0037735849056603776,
                0.0
            ],
            "tenpai_probs": [
                0.8992621402563711,
                0.9011573748330336,
                0.8956190610151783,
                0.8880957243292985,
                0.8781978094606067,
                0.8697078536844157,
                0.8539136582828623,
                0.8338992617748743,
                0.8096926171664809,
                0.7781807352414851,
                0.7384488129741225,
                0.6921714911406545,
                0.631006809986942,
                0.5486199162358566,
                0.44077890016877838,
                0.2276729559748427,
                0.10476190476190477
            ]
        },
        {
            "tile": 18,
            "syanten_down": false,
            "required_tiles": [
                {
                    "tile": 1,
                    "count": 2
                },
                {
                    "tile": 4,
                    "count": 4
                },
                {
                    "tile": 10,
                    "count": 4
                },
                {
                    "tile": 13,
                    "count": 4
                },
                {
                    "tile": 20,
                    "count": 2
                },
                {
                    "tile": 23,
                    "count": 3
                }
            ],
            "exp_values": [
                6752.173157238307,
                6450.384563782536,
                6127.389100360104,
                5781.945735173944,
                5414.115621427989,
                5023.993387285379,
                4608.479954218226,
                4167.539380240649,
                3702.3559420075837,
                3216.865899505906,
                2717.0215413618668,
                2207.531360497519,
                1696.7469454570012,
                1194.2365742584557,
                714.0291260013617,
                243.5098349335056,
                0.0
            ],
            "win_probs": [
                0.4926307606946265,
                0.46850254699301588,
                0.44736041186695699,
                0.4225251910538142,
                0.39304442080221227,
                0.36441455215155529,
                0.3312449684456648,
                0.29666662057898826,
                0.25997895779371046,
                0.22281388551953905,
                0.1857383031868652,
                0.14749268539892219,
                0.10869906736871923,
                0.0713674992388329,
                0.03819684107111368,
                0.012219227313566938,
                0.0
            ],
            "tenpai_probs": [
                0.9576479204139999,
                0.9576465306857096,
                0.9589239214893363,
                0.9556920643717075,
                0.9500213288639613,
                0.9435002424286251,
                0.931332581316354,
                0.918296895127295,
                0.8960392368752811,
                0.8723859047694583,
                0.8431146501933172,
                0.8052304988435857,
                0.742403199650194,
                0.6568275986897042,
                0.5424255401331753,
                0.3559748427672954,
                0.18095238095238098
            ]
        },
        {
            "tile": 19,
            "syanten_down": false,
            "required_tiles": [
                {
                    "tile": 10,
                    "count": 4
                },
                {
                    "tile": 13,
                    "count": 4
                },
                {
                    "tile": 18,
                    "count": 2
                },
                {
                    "tile": 20,
                    "count": 2
                }
            ],
            "exp_values": [
                3766.7549881200977,
                3566.1702798378466,
                3353.6925860566004,
                3129.37858721614,
                2893.185129621609,
                2645.496036315103,
                2387.006096684249,
                2119.3899770370396,
                1851.2463676117534,
                1580.3785067445329,
                1307.678925121711,
                1037.032421089297,
                773.8973943958968,
                525.8696360082197,
                290.7937211151331,
                82.54661290681874,
                0.0
            ],
            "win_probs": [
                0.3585051607883766,
                0.3372988537951007,
                0.31514036320734126,
                0.2917312303644996,
                0.2672701574358219,
                0.24181586764700023,
                0.21550173884644906,
                0.18895211878260755,
                0.1651293337579869,
                0.13809311605358544,
                0.11130844088554252,
                0.08528229369320131,
                0.06070245246261209,
                0.03847512188780633,
                0.01966731323105859,
                0.005750224618149146,
                0.0
            ],
            "tenpai_probs": [
                0.8772711330939823,
                0.8699154800508524,
                0.8619589199550376,
                0.8501705702678877,
                0.8355290139210494,
                0.8175453664787251,
                0.7956404514111086,
                0.7691262603924661,
                0.7371831737038177,
                0.6988318654994149,
                0.6528985185018855,
                0.597971581024098,
                0.5323477859224676,
                0.45665261578680718,
                0.36271758571176657,
                0.2456424079065589,
                0.1142857142857143
            ]
        },
        {
            "tile": 20,
            "syanten_down": false,
            "required_tiles": [
                {
                    "tile": 1,
                    "count": 2
                },
                {
                    "tile": 4,
                    "count": 4
                },
                {
                    "tile": 10,
                    "count": 4
                },
                {
                    "tile": 13,
                    "count": 4
                },
                {
                    "tile": 18,
                    "count": 2
                },
                {
                    "tile": 21,
                    "count": 3
                },
                {
                    "tile": 24,
                    "count": 4
                }
            ],
            "exp_values": [
                7870.521440607413,
                7588.868831294286,
                7275.781153673008,
                6929.14545413251,
                6546.990122325576,
                6127.617284515027,
                5669.787781385079,
                5172.9763484993059,
                4637.72610534472,
                4066.938312433891,
                3463.962743279496,
                2836.2631252877006,
                2195.7529528915376,
                1560.8244522197495,
                961.4221113363484,
                348.1365975362545,
                0.0
            ],
            "win_probs": [
                0.5865864904874817,
                0.5633899566838806,
                0.5377233707476474,
                0.5094398125308967,
                0.47841060775920127,
                0.44453806663435627,
                0.40777317690718398,
                0.36814001661084419,
                0.32539748015781386,
                0.28070445686735875,
                0.2340362723663242,
                0.18618520113244589,
                0.13836912742350403,
                0.09238310448561446,
                0.05077293834126843,
                0.01725067385444744,
                0.0
            ],
            "tenpai_probs": [
                0.9793094390350917,
                0.9825234583152528,
                0.9845443789164737,
                0.9850108981931421,
                0.9834570340475116,
                0.9792805771313334,
                0.9717015972525509,
                0.9597077250800985,
                0.9439350930506434,
                0.9190702795226822,
                0.8845142742178842,
                0.8372902974984384,
                0.7752596338603692,
                0.6896533369906671,
                0.5751635304095186,
                0.3885893980233604,
                0.21904761904761908
            ]
        },
        {
            "tile": 21,
            "syanten_down": true,
            "required_tiles": [
                {
                    "tile": 1,
                    "count": 2
                },
                {
                    "tile": 4,
                    "count": 4
                },
                {
                    "tile": 10,
                    "count": 4
                },
                {
                    "tile": 11,
                    "count": 2
                },
                {
                    "tile": 12,
                    "count": 3
                },
                {
                    "tile": 13,
                    "count": 4
                },
                {
                    "tile": 18,
                    "count": 2
                },
                {
                    "tile": 19,
                    "count": 3
                },
                {
                    "tile": 20,
                    "count": 2
                },
                {
                    "tile": 21,
                    "count": 3
                },
                {
                    "tile": 22,
                    "count": 3
                },
                {
                    "tile": 23,
                    "count": 3
                },
                {
                    "tile": 24,
                    "count": 4
                }
            ],
            "exp_values": [
                4293.374893400593,
                3966.38781217628,
                3630.3767499068478,
                3286.6929078708637,
                2937.163065250473,
                2584.0678822370107,
                2230.437078301842,
                1880.145914622043,
                1538.0342393549277,
                1210.0479794620565,
                903.3556660022628,
                626.3959283905491,
                387.70397390328938,
                197.38916985482443,
                65.62358626929572,
                0.0,
                0.0
            ],
            "win_probs": [
                0.3304939643731777,
                0.3035311661199683,
                0.27593658546689206,
                0.24784426275693537,
                0.21942939520079003,
                0.19101476258328729,
                0.16281064718221453,
                0.13517905572790604,
                0.10856167008723428,
                0.083486171182757,
                0.06056601197840736,
                0.040486884294496049,
                0.023836727556009689,
                0.011323802495259616,
                0.003390684434592034,
                0.0,
                0.0
            ],
            "tenpai_probs": [
                0.8497998159125022,
                0.8304118159249925,
                0.8082527467054655,
                0.7829247526496924,
                0.7539921677423478,
                0.7202857954737146,
                0.681631926808005,
                0.6373938345354104,
                0.5869497188803369,
                0.5297770294136808,
                0.4656045817962476,
                0.39467899881714565,
                0.3135541268089126,
                0.2269805349597273,
                0.13959745068896896,
                0.05471698113207547,
                0.0
            ]
        },
        {
            "tile": 22,
            "syanten_down": true,
            "required_tiles": [
                {
                    "tile": 0,
                    "count": 4
                },
                {
                    "tile": 1,
                    "count": 2
                },
                {
                    "tile": 2,
                    "count": 3
                },
                {
                    "tile": 3,
                    "count": 3
                },
                {
                    "tile": 4,
                    "count": 4
                },
                {
                    "tile": 10,
                    "count": 4
                },
                {
                    "tile": 11,
                    "count": 2
                },
                {
                    "tile": 12,
                    "count": 3
                },
                {
                    "tile": 13,
                    "count": 4
                },
                {
                    "tile": 18,
                    "count": 2
                },
                {
                    "tile": 19,
                    "count": 3
                },
                {
                    "tile": 20,
                    "count": 2
                },
                {
                    "tile": 21,
                    "count": 3
                },
                {
                    "tile": 22,
                    "count": 3
                },
                {
                    "tile": 23,
                    "count": 3
                },
                {
                    "tile": 24,
                    "count": 4
                },
                {
                    "tile": 25,
                    "count": 4
                }
            ],
            "exp_values": [
                5119.377513505253,
                4762.372687161286,
                4392.767894646788,
                4011.4186930942748,
                3619.6257198247055,
                3219.2628624431129,
                2812.940176103971,
                2404.210912163063,
                1997.833981961977,
                1600.1049750049745,
                1219.2693769376113,
                866.028420014491,
                551.4697999707408,
                289.5539753192725,
                98.992388000259,
                0.0,
                0.0
            ],
            "win_probs": [
                0.34655459608802149,
                0.3209787670684804,
                0.2945834472165837,
                0.26744870527540517,
                0.23969086459555703,
                0.21147275816436923,
                0.18301672677227827,
                0.1546210460350399,
                0.12668056250730487,
                0.0997123212735146,
                0.07438671367613635,
                0.051563797752136177,
                0.03147953860129169,
                0.015582388444317556,
                0.0048819810061213699,
                0.0,
                0.0
            ],
            "tenpai_probs": [
                0.8615427517415221,
                0.8461216398651921,
                0.8284378309550075,
                0.808088832749369,
                0.7845941363563441,
                0.7573838022302035,
                0.7257911042326708,
                0.689057248949711,
                0.6463653983565234,
                0.5969402648259654,
                0.5402889261469507,
                0.4767402193881029,
                0.3930475178677713,
                0.29519785212490798,
                0.18429772191013597,
                0.06576819407008088,
                0.0
            ]
        },
        {
            "tile": 23,
            "syanten_down": false,
            "required_tiles": [
                {
                    "tile": 1,
                    "count": 2
                },
                {
                    "tile": 4,
                    "count": 4
                },
                {
                    "tile": 10,
                    "count": 4
                },
                {
                    "tile": 13,
                    "count": 4
                },
                {
                    "tile": 18,
                    "count": 2
                },
                {
                    "tile": 21,
                    "count": 3
                }
            ],
            "exp_values": [
                7152.596119661193,
                6835.606180958296,
                6492.293915690597,
                6121.753259623807,
                5723.366110850461,
                5296.9274024152459,
                4842.818140523888,
                4362.203120050024,
                3857.662127932985,
                3335.351213329984,
                2799.273547777575,
                2255.9699995991338,
                1715.4643027872908,
                1193.7097082484295,
                716.106290272783,
                249.94765097681046,
                0.0
            ],
            "win_probs": [
                0.48779557724423747,
                0.46473888839822916,
                0.4398207870130368,
                0.41299030735649147,
                0.3842214069160181,
                0.3535232455802611,
                0.3209981760277281,
                0.286680069065141,
                0.251872174128446,
                0.2155973995597613,
                0.17832200872150354,
                0.1402143656338424,
                0.10317425308810746,
                0.06810756604737678,
                0.03717493345424926,
                0.012219227313566938,
                0.0
            ],
            "tenpai_probs": [
                0.9571571833458958,
                0.957069157223547,
                0.9553546937944618,
                0.9516225251997749,
                0.9453874794115961,
                0.9360465855215646,
                0.9228486686896995,
                0.9048555212762495,
                0.8865271966004518,
                0.8628775699252967,
                0.8286239518046605,
                0.7774891504098038,
                0.7176274499517328,
                0.6313654171086723,
                0.5189678481161464,
                0.3528301886792454,
                0.18095238095238098
            ]
        }
    ]
}